agm/__init__.py
agm/agm.py
agm/docs.py
agm/exceptions.py
agm/executor.py
agm/google_auth.py
agm/utils.py
agm-0.1.9.dist-info/LICENSE
agm-0.1.9.dist-info/METADATA
agm-0.1.9.dist-info/WHEEL
agm-0.1.9.dist-info/entry_points.txt
agm-0.1.9.dist-info/top_level.txt
agm-0.1.9.dist-info/RECORD
