Metadata-Version: 2.1
Name: agm
Version: 0.1.9
Summary: An (unofficial) command line interface for Google APIs
Home-page: https://github.com/Cloudbakers/agm
Author: Alex Wennerberg
Author-email: awennerberg@cloudbakers.com
License: Apache
Project-URL: Documentation, https://agm.readthedocs.io
Project-URL: Source, https://github.com/Cloudbakers/agm/
Project-URL: Tracker, https://github.com/Cloudbakers/agm/issues
Keywords: google google-apis gcp gsuite cli
Platform: UNKNOWN
Classifier: Development Status :: 3 - Alpha
Classifier: Programming Language :: Python :: 3.5
Classifier: Programming Language :: Python :: 3.6
Classifier: Programming Language :: Python :: 3.7
Classifier: License :: OSI Approved :: Apache Software License
Requires-Python: >=3.5
Requires-Dist: colorful
Requires-Dist: google-api-python-client
Requires-Dist: oauth2client
Requires-Dist: requests
Requires-Dist: requests-cache
Requires-Dist: tqdm
